{
    "nei":[
        {
        "id":1,
        "name":"旅游1",
        "img":"https://i02piccdn.sogoucdn.com/ca4e204d8996e403",
        "jin_foot":"[花花鸟]2019年全年计划，中国的圣托里尼,..."
        },
        {
        "id":2,
        "name":"旅游2",
        "img":"https://i01piccdn.sogoucdn.com/28eb9f393907cdd2",
        "jin_foot":"[花花鸟]2019年全年计划，中国的圣托里尼,..."
        },
        {
        "id":3,
        "name":"旅游3",
        "img":"https://i02piccdn.sogoucdn.com/f612cc7c6d42ac03",
        "jin_foot":"[花花鸟]2019年全年计划，中国的圣托里尼,..."
        },
        {
        "id":4,
        "name":"旅游4",
        "img":"https://img01.sogoucdn.com/app/a/100520093/b692ca88cf40622d-c4c351c548f54192-6fe60afa2548e8e3573a641bc8a1d61d.jpg",
        "jin_foot":"[花花鸟]2019年全年计划，中国的圣托里尼,..."
        },
        {
        "id":5,
        "name":"旅游5",
        "img":"https://i03piccdn.sogoucdn.com/6756d55c98e339f0",
        "jin_foot":"[花花鸟]2019年全年计划，中国的圣托里尼,..."
        },
        {
        "id":6,
        "name":"旅游6",
        "img":"https://i04piccdn.sogoucdn.com/316f63374e825f88",
        "jin_foot":"[花花鸟]2019年全年计划，中国的圣托里尼,..."
        },
        {
        "id":7,
        "name":"旅游7",
        "img":"https://i03piccdn.sogoucdn.com/6756d55c98e339f0",
        "jin_foot":"[花花鸟]2019年全年计划，中国的圣托里尼,..."
        },
        {
        "id":8,
        "name":"旅游8",
        "img":"https://i04piccdn.sogoucdn.com/316f63374e825f88",
        "jin_foot":"[花花鸟]2019年全年计划，中国的圣托里尼,..."
        },
        {
        "id":9,
        "name":"旅游9",
        "img":"https://img02.sogoucdn.com/app/a/100520093/30c40e020f63f81f-85679ec6a342f6f1-852857942ff2617a603a1dfe05738c96.jpg",
        "jin_foot":"[花花鸟]2019年全年计划，中国的圣托里尼,..."
        },
        {
        "id":10,
        "name":"旅游10",
        "img":"https://i03piccdn.sogoucdn.com/6756d55c98e339f0",
        "jin_foot":"[花花鸟]2019年全年计划，中国的圣托里尼,..."
        }
    ]
}